{
  "mode": "pre",
  "tag": "rc",
  "initialVersions": {
    "docs": "15.2.49",
    "e2e": "15.2.49",
    "@baloise/ds-nx": "19.8.3",
    "@baloise/output-target-angular": "0.0.0",
    "@baloise/output-target-web": "0.0.0",
    "@baloise/ds-angular": "19.8.3",
    "@baloise/ds-angular-common": "19.8.3",
    "@baloise/ds-angular-module": "19.8.3",
    "@baloise/ds-brand-icons": "19.8.3",
    "@baloise/ds-core": "19.8.3",
    "@baloise/ds-devkit": "19.8.3",
    "@baloise/ds-favicons": "19.8.3",
    "@baloise/ds-fonts": "19.8.3",
    "@baloise/ds-icons": "19.8.3",
    "@baloise/ds-maps": "19.8.3",
    "@baloise/ds-playwright": "19.8.3",
    "@baloise/ds-react": "19.8.3",
    "@baloise/ds-styles": "19.8.3",
    "@baloise/ds-table": "19.8.3",
    "@baloise/ds-testing": "19.8.3",
    "@baloise/ds-tokens": "19.8.3"
  },
  "changesets": []
}
